setup.cfg
setup.py
NewRelicApiParser/__init__.py
NewRelicApiParser/Base/__init__.py
NewRelicApiParser/CustomExceptions/__init__.py
NewRelicApiParser/Graph/__init__.py
NewRelicApiParser/Insights/__init__.py
NewRelicApiParser/REST/__init__.py
NewRelicApiParser/REST/AlertsConditions/__init__.py
NewRelicApiParser/REST/AlertsEvents/__init__.py
NewRelicApiParser/REST/AlertsPolicies/__init__.py
NewRelicApiParser/REST/AlertsViolations/__init__.py
NewRelicApiParser/REST/Applications/__init__.py
NewRelicApiParser/REST/BrowserApplications/__init__.py
NewRelicApiParser/REST/KeyTransactions/__init__.py
NewRelicApiParser/REST/Plugins/__init__.py
NewRelicApiParser/REST/Users/__init__.py
newrelic_api_parser.egg-info/PKG-INFO
newrelic_api_parser.egg-info/SOURCES.txt
newrelic_api_parser.egg-info/dependency_links.txt
newrelic_api_parser.egg-info/requires.txt
newrelic_api_parser.egg-info/top_level.txt